setup.cfg
setup.py
GOCPI/CreateCases.py
GOCPI/Energysystems.py
GOCPI/Forecasting.py
GOCPI/Navigation.py
GOCPI/Optimisation.py
GOCPI/__init__.py
GOCPI.egg-info/PKG-INFO
GOCPI.egg-info/SOURCES.txt
GOCPI.egg-info/dependency_links.txt
GOCPI.egg-info/not-zip-safe
GOCPI.egg-info/top_level.txt