Metadata-Version: 1.0
Name: GOCPI
Version: 3.0.9320
Summary: User Defined Functions and Energy Systems Data for GOCPI Project
Home-page: UNKNOWN
Author: UNKNOWN
Author-email: connormcdowall@gmail.com
License: UNKNOWN
Platform: UNKNOWN
